{
  "inventory": [
    {
      "inventoryId": "INV-AG6FZX",
      "color": "Castilian Pink",
      "code": "S170-3",
      "kilnSpec": "KP003",
      "brand": "Behr",
      "finish": "Eggshell",
      "hex": "#D3B2A9",
      "quantity": "2",
      "lowStock": "0",
      "location": "Lehi 1 Storage",
      "notes": ""
    },
    {
      "inventoryId": "INV-Z9VGQG",
      "color": "Green Tea Leaf",
      "code": "PPG1128-5",
      "kilnSpec": "KP006",
      "brand": "PPG",
      "finish": "Eggshell",
      "hex": "#929988",
      "quantity": "5",
      "lowStock": "0",
      "location": "Lehi 1 Storage",
      "notes": ""
    },
    {
      "inventoryId": "INV-9WK7ER",
      "color": "Pure White",
      "code": "SW7005",
      "kilnSpec": "KP001",
      "brand": "Sherwin Williams",
      "finish": "Eggshell",
      "hex": "#EDEBE5",
      "quantity": "1",
      "lowStock": "0",
      "location": "Lehi 1 Storage",
      "notes": ""
    },
    {
      "inventoryId": "INV-IO200I",
      "color": "Tempe Star",
      "code": "SW6229",
      "kilnSpec": "KP017",
      "brand": "Sherwin Williams",
      "finish": "Eggshell",
      "hex": "#466067",
      "quantity": "7",
      "lowStock": "0",
      "location": "Lehi 1 storage",
      "notes": ""
    },
    {
      "inventoryId": "INV-PJQQ3T",
      "color": "Blue Grey",
      "code": "",
      "kilnSpec": "",
      "brand": "",
      "finish": "",
      "hex": "#cccccc",
      "quantity": "",
      "lowStock": "",
      "location": "",
      "notes": ""
    },
    {
      "inventoryId": "INV-TAU85X",
      "color": "Dark Green",
      "code": "",
      "kilnSpec": "",
      "brand": "",
      "finish": "",
      "hex": "#cccccc",
      "quantity": "",
      "lowStock": "",
      "location": "",
      "notes": ""
    }
  ],
  "floors": {
    "1st-floor": {
      "rooms": [
        {
          "id": "55084f55-4b72-4eb1-858a-4502ea7cc9f3",
          "name": "Cafe",
          "notes": "Confirmed Color.",
          "paints": [
            {
              "inventoryId": "INV-IO200I"
            }
          ],
          "primaryPaintId": "INV-IO200I",
          "points": [
            {
              "x": 901.6530229821618,
              "y": 9.869978323522867
            },
            {
              "x": 901.1808657353549,
              "y": 148.68420819556775
            },
            {
              "x": 1097.126123160189,
              "y": 148.68420819556775
            },
            {
              "x": 1097.126123160189,
              "y": 88.72023814880008
            },
            {
              "x": 1087.2108209772455,
              "y": 89.19239539326281
            },
            {
              "x": 1087.6829782240525,
              "y": 61.33511796996128
            },
            {
              "x": 1058.4092289220291,
              "y": 60.86296072549855
            },
            {
              "x": 1057.9370716752221,
              "y": 8.453506590134651
            }
          ]
        },
        {
          "id": "2ec5bd07-fd82-4cc6-8e83-bc057d1e2fa4",
          "name": "Community Entryway",
          "notes": "Confirmed Color. Unknown if its a kiln color.",
          "paints": [
            {
              "inventoryId": "INV-PJQQ3T"
            }
          ],
          "primaryPaintId": "INV-PJQQ3T",
          "points": [
            {
              "x": 1118.1730342558794,
              "y": 61.11423941538301
            },
            {
              "x": 1152.368521036588,
              "y": 61.33511796996128
            },
            {
              "x": 1152.7789922813097,
              "y": 234.14402744851253
            },
            {
              "x": 1096.4207177827516,
              "y": 234.14402744851253
            },
            {
              "x": 1097.126123160189,
              "y": 87.30376641541186
            },
            {
              "x": 1118.1730342558794,
              "y": 88.79900550068372
            }
          ]
        },
        {
          "id": "0157933d-e38a-4801-ad07-9b356cf761ec",
          "name": "Basecamp 4",
          "notes": "Not Confirmed Color.",
          "paints": [
            {
              "inventoryId": "INV-TAU85X"
            }
          ],
          "primaryPaintId": "INV-TAU85X",
          "points": [
            {
              "x": 1326.7975240663304,
              "y": 158.01092071393552
            },
            {
              "x": 1320.8650741191136,
              "y": 234.14402744851253
            },
            {
              "x": 1391.0657318278438,
              "y": 234.14402744851253
            },
            {
              "x": 1389.0882485121049,
              "y": 158.01092071393552
            }
          ]
        },
        {
          "id": "36cc5ba1-acae-45a3-b419-8ad85335b059",
          "name": "Kitchen Walls",
          "notes": "Unknown Color. Not a color we have in the storage room.",
          "paints": [],
          "primaryPaintId": null,
          "points": [
            {
              "x": 1580.1910583480876,
              "y": 155.55618313267976
            },
            {
              "x": 1579.9153884809064,
              "y": 252.93011872068087
            },
            {
              "x": 1611.2238711159048,
              "y": 253.08788368362232
            },
            {
              "x": 1611.626894658344,
              "y": 155.55618313267976
            }
          ]
        },
        {
          "id": "995c9ddc-ddac-4c13-a682-3a373ba26562",
          "name": "Silver Lake Conference Room",
          "notes": "",
          "paints": [
            {
              "inventoryId": "INV-IO200I"
            }
          ],
          "primaryPaintId": "INV-IO200I",
          "points": [
            {
              "x": 1582.6091996027228,
              "y": 254.29695435160923
            },
            {
              "x": 1581.892871796645,
              "y": 379.4890493963413
            },
            {
              "x": 1683.7332625571971,
              "y": 380.4777910422449
            },
            {
              "x": 1683.7332625571971,
              "y": 254.90760201248804
            }
          ]
        },
        {
          "id": "55e4111e-b17c-42e2-880f-b7e5e5bc6134",
          "name": "PS 14",
          "notes": "Not Confirmed Color.",
          "paints": [
            {
              "inventoryId": "INV-IO200I"
            }
          ],
          "primaryPaintId": "INV-IO200I",
          "points": [
            {
              "x": 1785.9649625353084,
              "y": 61.01006756810179
            },
            {
              "x": 1785.9649625353084,
              "y": 277.7963754126882
            },
            {
              "x": 1938.1278709465469,
              "y": 277.3380534087884
            },
            {
              "x": 1938.1278709465469,
              "y": 61.01006756810179
            }
          ]
        },
        {
          "id": "c876be71-c780-4cf1-9366-231562caf430",
          "name": "Community Area Walls",
          "notes": "Confirmed Color.",
          "paints": [
            {
              "inventoryId": "INV-Z9VGQG"
            }
          ],
          "primaryPaintId": "INV-Z9VGQG",
          "points": [
            {
              "x": 1785.0483185087346,
              "y": 278.71299144010686
            },
            {
              "x": 1783.673352468874,
              "y": 464.79171101177946
            },
            {
              "x": 1879.4626532458285,
              "y": 465.25003298116775
            },
            {
              "x": 1879.9209752591153,
              "y": 277.79634750133016
            }
          ]
        },
        {
          "id": "eec1272f-4e18-4f04-b94b-90e554db8ef8",
          "name": "Basecamp 3",
          "notes": "Not Confirmed Color.",
          "paints": [
            {
              "inventoryId": "INV-TAU85X"
            }
          ],
          "primaryPaintId": "INV-TAU85X",
          "points": [
            {
              "x": 1581.5265041961268,
              "y": 605.4003611616151
            },
            {
              "x": 1580.129670874559,
              "y": 683.6230297185234
            },
            {
              "x": 1716.6631212070051,
              "y": 683.4279089434631
            },
            {
              "x": 1716.3301704364915,
              "y": 605.5174336125858
            }
          ]
        },
        {
          "id": "479c7d2a-091f-4742-a682-6d48a0abec16",
          "name": "Whiteboard room 2",
          "notes": "Confirmed Color.",
          "paints": [
            {
              "inventoryId": "INV-PJQQ3T"
            }
          ],
          "primaryPaintId": "INV-PJQQ3T",
          "points": [
            {
              "x": 1549.521834409178,
              "y": 603.5197291169222
            },
            {
              "x": 1582.4839606900243,
              "y": 603.5197291169222
            },
            {
              "x": 1582.1510099195107,
              "y": 683.4279089434631
            },
            {
              "x": 1549.3994230560027,
              "y": 683.6230297185234
            }
          ]
        },
        {
          "id": "cdbb0edf-c44d-4506-a6b8-96ca3c426741",
          "name": "Whiteboard room 1",
          "notes": "Confirmed Color.",
          "paints": [
            {
              "inventoryId": "INV-PJQQ3T"
            }
          ],
          "primaryPaintId": "INV-PJQQ3T",
          "points": [
            {
              "x": 1440.4464239736976,
              "y": 604.0035277945275
            },
            {
              "x": 1473.9704236913299,
              "y": 604.0035277945275
            },
            {
              "x": 1472.5735903697619,
              "y": 683.6230297185234
            },
            {
              "x": 1440.4464239736976,
              "y": 683.6230297185234
            }
          ]
        },
        {
          "id": "9e584e64-8d5c-4053-bf79-4f2adf66cf49",
          "name": "Arches Conference Room",
          "notes": "Confirmed Color.",
          "paints": [
            {
              "inventoryId": "INV-AG6FZX"
            }
          ],
          "primaryPaintId": "INV-AG6FZX",
          "points": [
            {
              "x": 1111.0946363019275,
              "y": 349.613054349654
            },
            {
              "x": 1197.5307407907205,
              "y": 349.99216006552354
            },
            {
              "x": 1197.3974260208631,
              "y": 419.6215339959506
            },
            {
              "x": 1211.3657592365432,
              "y": 419.6215339959506
            },
            {
              "x": 1211.5576524840772,
              "y": 496.3269663911605
            },
            {
              "x": 1110.7155305804852,
              "y": 496.3269663911605
            }
          ]
        },
        {
          "id": "5ea3e895-f098-4705-b6ac-b1abf37232de",
          "name": "Front Desk Seating Area",
          "notes": "Black, not sure which.",
          "paints": [],
          "primaryPaintId": null,
          "points": [
            {
              "x": 1097.183657878627,
              "y": 604.5074746850111
            },
            {
              "x": 1236.144194388106,
              "y": 604.5074746850111
            },
            {
              "x": 1235.757117684737,
              "y": 683.4711254464003
            },
            {
              "x": 1097.183657878627,
              "y": 683.0840487269817
            }
          ]
        },
        {
          "id": "c922bad5-492f-42ea-b3df-81e0004b6536",
          "name": "Support Offices",
          "notes": "Confirmed Color.",
          "paints": [
            {
              "inventoryId": "INV-TAU85X"
            }
          ],
          "primaryPaintId": "INV-TAU85X",
          "points": [
            {
              "x": 482.11356613383396,
              "y": 510.8813364733677
            },
            {
              "x": 557.0103436725186,
              "y": 510.4218470540738
            },
            {
              "x": 556.2509314211449,
              "y": 683.6230297185234
            },
            {
              "x": 480.27560840282325,
              "y": 683.1898687085949
            }
          ]
        }
      ]
    },
    "2nd-floor": {
      "rooms": [
        {
          "id": "4117e917-3742-48ca-a6c6-8c71019b9477",
          "name": "Timpanogos Meeting Room",
          "notes": "Confirmed Color.",
          "paints": [
            {
              "inventoryId": "INV-PJQQ3T"
            }
          ],
          "primaryPaintId": "INV-IO200I",
          "points": [
            {
              "x": 774.4029928863628,
              "y": 461.4085888826505
            },
            {
              "x": 775.0377198425858,
              "y": 545.5099140113758
            },
            {
              "x": 851.839681545585,
              "y": 545.1925505203242
            },
            {
              "x": 852.474408501808,
              "y": 461.72595237370234
            }
          ]
        },
        {
          "id": "72f12a84-570d-4d87-8a15-a5d76c1ff5a2",
          "name": "Green River Conference Room",
          "notes": "",
          "paints": [
            {
              "inventoryId": "INV-Z9VGQG"
            }
          ],
          "primaryPaintId": "INV-Z9VGQG",
          "points": [
            {
              "x": 481.789985595671,
              "y": 269.50128202102525
            },
            {
              "x": 556.5776002329987,
              "y": 269.0452599910768
            },
            {
              "x": 557.0336222734703,
              "y": 473.79915143791413
            },
            {
              "x": 481.789985595671,
              "y": 473.79915143791413
            }
          ]
        },
        {
          "id": "363c84b1-3135-4210-a90a-5a101ae67240",
          "name": "Tea Kitchen",
          "notes": "",
          "paints": [
            {
              "inventoryId": "INV-AG6FZX"
            }
          ],
          "primaryPaintId": "INV-AG6FZX",
          "points": [
            {
              "x": 413.3866795249444,
              "y": 303.7029342671562
            },
            {
              "x": 414.2987236058874,
              "y": 251.71642285303713
            },
            {
              "x": 582.1148344994034,
              "y": 249.43631270329507
            },
            {
              "x": 580.7467683779889,
              "y": 488.84787842621176
            },
            {
              "x": 479.05385335284194,
              "y": 491.12798857595385
            },
            {
              "x": 479.05385335284194,
              "y": 477.44732767750145
            },
            {
              "x": 561.5938426781853,
              "y": 476.991305647553
            },
            {
              "x": 560.6817985972423,
              "y": 265.39708375148956
            },
            {
              "x": 478.1418092718989,
              "y": 265.853105781438
            },
            {
              "x": 476.7737431504844,
              "y": 303.2469122372078
            }
          ]
        },
        {
          "id": "e6abb9de-fb68-43b7-8938-114e3afc07ca",
          "name": "Maker Space",
          "notes": "",
          "paints": [
            {
              "inventoryId": "INV-PJQQ3T"
            }
          ],
          "primaryPaintId": "INV-PJQQ3T",
          "points": [
            {
              "x": 1213.4828845724755,
              "y": 475.32521190424325
            },
            {
              "x": 1214.0291677330704,
              "y": 551.8048564330296
            },
            {
              "x": 1303.0733229100301,
              "y": 551.2585732578241
            },
            {
              "x": 1303.0733229100301,
              "y": 475.32521190424325
            }
          ]
        },
        {
          "id": "53b319a5-fffb-4ba6-9972-ef0839b9ab4e",
          "name": "Kitchen",
          "notes": "Dark blue like downstairs.",
          "paints": [],
          "primaryPaintId": null,
          "points": [
            {
              "x": 1221.6771319813981,
              "y": 320.7270899922931
            },
            {
              "x": 1346.775975757618,
              "y": 321.2733731674987
            },
            {
              "x": 1346.775975757618,
              "y": 429.9837250334166
            },
            {
              "x": 1222.2234151419927,
              "y": 428.8911586830053
            }
          ]
        }
      ]
    },
    "5th-floor": {
      "rooms": []
    }
  }
}